Metadata-Version: 1.0
Name: python-microsoft-linkedin
Version: 0.0.1
Summary: Microsoft Linkedin Api Wrapper on python 3.6
Home-page: https://github.com/alisterion/python-microsoft-linkedin
Author: Alex Vorobiov
Author-email: a.vorobyov@bvblogic.com
License: MIT
Keywords: python linkedin v2
Platform: UNKNOWN
